python_metadata_parser/__init__.py
python_metadata_parser/__main__.py
python_metadata_parser/_version.py
python_metadata_parser/core_metadata.py
python_metadata_parser/pep0723.py
python_metadata_parser/py.typed
python_metadata_parser/pyproject.py
python_metadata_parser/wheel.py
python_metadata_parser-0.1.3.dist-info/METADATA
python_metadata_parser-0.1.3.dist-info/WHEEL
python_metadata_parser-0.1.3.dist-info/entry_points.txt
python_metadata_parser-0.1.3.dist-info/licenses/LICENSE.txt
python_metadata_parser-0.1.3.dist-info/RECORD
